mathmaker/__init__.py
mathmaker/cli.py
mathmaker/core/__init__.py
mathmaker/core/env.py
mathmaker/data/anglessets.db-dist
mathmaker/data/anglessets_db_index.json
mathmaker/data/db_index.json
mathmaker/data/extra_translations.yaml
mathmaker/data/fonts_list.txt
mathmaker/data/frameworks/algebra/expand.yaml
mathmaker/data/frameworks/calculation/order_of_operations.yaml
mathmaker/data/frameworks/exercise.xsd
mathmaker/data/frameworks/geometry/angles.yaml
mathmaker/data/frameworks/geometry/converse_contrapositive_pythagorean_theorem.yaml
mathmaker/data/frameworks/geometry/pythagorean_theorem.yaml
mathmaker/data/frameworks/geometry/trigonometry/trigonometry_calculate_angle.xml
mathmaker/data/frameworks/geometry/trigonometry/trigonometry_calculate_length.xml
mathmaker/data/frameworks/geometry/trigonometry/trigonometry_cos_angle.xml
mathmaker/data/frameworks/geometry/trigonometry/trigonometry_cos_formulae.xml
mathmaker/data/frameworks/geometry/trigonometry/trigonometry_cos_length.xml
mathmaker/data/frameworks/geometry/trigonometry/trigonometry_formulae.xml
mathmaker/data/frameworks/geometry/trigonometry/trigonometry_sin_angle.xml
mathmaker/data/frameworks/geometry/trigonometry/trigonometry_sin_formulae.xml
mathmaker/data/frameworks/geometry/trigonometry/trigonometry_sin_length.xml
mathmaker/data/frameworks/geometry/trigonometry/trigonometry_tan_angle.xml
mathmaker/data/frameworks/geometry/trigonometry/trigonometry_tan_formulae.xml
mathmaker/data/frameworks/geometry/trigonometry/trigonometry_tan_length.xml
mathmaker/data/frameworks/geometry/trigonometry/trigonometry_vocabulary.xml
mathmaker/data/frameworks/index.json
mathmaker/data/frameworks/layout.xsd
mathmaker/data/frameworks/mental_calculation/aside.yaml
mathmaker/data/frameworks/mental_calculation/y0b1.yaml
mathmaker/data/frameworks/mental_calculation/y0b2.yaml
mathmaker/data/frameworks/mental_calculation/y0b3.yaml
mathmaker/data/frameworks/mental_calculation/y0b4.yaml
mathmaker-0.8.13.dist-info/LICENSE
mathmaker-0.8.13.dist-info/METADATA
mathmaker-0.8.13.dist-info/WHEEL
mathmaker-0.8.13.dist-info/entry_points.txt
mathmaker-0.8.13.dist-info/RECORD
