Metadata-Version: 2.3
Name: mathmaker
Version: 0.8.13
Summary: Mathmaker creates automatically elementary maths exercises and their (detailed) answers.
License: GPL-3.0-or-later
Author: Nicolas Hainaux
Author-email: nh.techn@posteo.net
Requires-Python: >=3.9,<3.13
Classifier: License :: OSI Approved :: GNU General Public License v3 or later (GPLv3+)
Classifier: Programming Language :: Python :: 3
Classifier: Programming Language :: Python :: 3.9
Classifier: Programming Language :: Python :: 3.10
Classifier: Programming Language :: Python :: 3.11
Classifier: Programming Language :: Python :: 3.12
Requires-Dist: intspan (>=1.6.1,<2.0.0)
Requires-Dist: mathmakerlib (>=0.7.30,<0.8.0)
Requires-Dist: microlib (>=1.10.4,<2.0.0)
Requires-Dist: packaging (>=25,<26)
Requires-Dist: polib (>=1.2.0,<2.0.0)
Requires-Dist: python-daemon (>=3.1.2,<4.0.0)
Requires-Dist: ruamel.yaml (>=0.18.10,<0.19.0)
Requires-Dist: waitress (>=3.0.2,<4.0.0)
